capricorn/Vocab.py
capricorn/VocabularyProcessor.py
capricorn/__init__.py
capricorn/__version__.py
capricorn-0.1.2.dist-info/LICENSE
capricorn-0.1.2.dist-info/METADATA
capricorn-0.1.2.dist-info/WHEEL
capricorn-0.1.2.dist-info/top_level.txt
capricorn-0.1.2.dist-info/RECORD
