Metadata-Version: 2.1
Name: capricorn
Version: 0.1.2
Summary: nlp vocabulary builder and embedding loader
Home-page: https://github.com/WenchenLi/capricorn
Author: Wenchen Li
Author-email: wenchen.li.cs@gmail.com
License: MIT
Platform: UNKNOWN
Classifier: License :: OSI Approved :: MIT License
Classifier: Programming Language :: Python
Classifier: Programming Language :: Python :: 3
Classifier: Programming Language :: Python :: 3.7
Classifier: Programming Language :: Python :: Implementation :: CPython
Classifier: Programming Language :: Python :: Implementation :: PyPy
Requires-Python: >=3.6.0
